AUTHOR
LICENSE
MANIFEST.in
README.rst
setup.cfg
setup.py
cwbrowser/__init__.py
cwbrowser/configure.py
cwbrowser/cw_connection.py
cwbrowser/info.py
cwbrowser/utils.py
cwbrowser.egg-info/PKG-INFO
cwbrowser.egg-info/SOURCES.txt
cwbrowser.egg-info/dependency_links.txt
cwbrowser.egg-info/requires.txt
cwbrowser.egg-info/top_level.txt
doc/source/_static/cwbrowser.png
doc/source/_static/nsap.png
doc/source/_static/carousel/dbschema.png
doc/source/_static/carousel/sds.png