Metadata-Version: 1.1
Name: cwbrowser
Version: 2.2.1
Summary: Python package to request CubicWeb services.
Home-page: https://github.com/neurospin/rql_download.git
Author: Antoine Grigis - antoine.grigis@cea.fr
Author-email: antoine.grigis@cea.fr
License: CeCILLB
Platform: OS Independent
Classifier: Development Status :: 4 - Beta
Classifier: Environment :: Console
Classifier: Environment :: Web Environment
Classifier: Intended Audience :: Developers
Classifier: Intended Audience :: Science/Research
Classifier: Intended Audience :: Education
Classifier: Operating System :: OS Independent
Classifier: Programming Language :: Python :: 2.7
Classifier: Topic :: Scientific/Engineering
Classifier: Topic :: Utilities
